pkg_py-0.1.0.dist-info/METADATA
pkg_py-0.1.0.dist-info/WHEEL
pkg_py-0.1.0.dist-info/entry_points.txt
pkg_py/__init__.py
pkg_py/hi.py
pkg_py-0.1.0.dist-info/RECORD
