Metadata-Version: 2.1
Name: pkg_py
Version: 0.1.0
Summary: packaging python template
Author-Email: abdelrahman abounida <abdelrahmanaboneda@gmail.com>
License: MIT
Requires-Python: >=3.11
Requires-Dist: loguru>=0.7.3
